gym_pyraminx/__init__.py
gym_pyraminx/envs/__init__.py
gym_pyraminx/envs/pyraminx_env.py
gym_pyraminx-0.0.1.dist-info/METADATA
gym_pyraminx-0.0.1.dist-info/WHEEL
gym_pyraminx-0.0.1.dist-info/top_level.txt
gym_pyraminx-0.0.1.dist-info/RECORD
